exiffusion/__init__.py
exiffusion/apple.py
exiffusion/cli.py
exiffusion/color.py
exiffusion/exif.py
exiffusion/font.py
exiffusion/fuse.py
exiffusion/geo.py
exiffusion/overlay.py
exiffusion/assets/WorkSans-Medium.otf
exiffusion/assets/unifont-15.1.05.otf
exiffusion-0.0.5.dist-info/LICENSE
exiffusion-0.0.5.dist-info/METADATA
exiffusion-0.0.5.dist-info/WHEEL
exiffusion-0.0.5.dist-info/entry_points.txt
exiffusion-0.0.5.dist-info/top_level.txt
exiffusion-0.0.5.dist-info/RECORD
