Metadata-Version: 2.1
Name: exiffusion
Version: 0.0.5
Summary: Overlay Exif metadata onto photos.
Author-email: Barry Li <barry@barryli.ca>
Project-URL: Homepage, https://github.com/JFBarryLi/ExifFusion
Project-URL: Issues, https://github.com/JFBarryLi/ExifFusion/issues
Classifier: Programming Language :: Python :: 3
Classifier: Operating System :: OS Independent
Requires-Python: >=3.12
License-File: LICENSE
Requires-Dist: pytest ~=8.2
Requires-Dist: pydantic ~=2.7
Requires-Dist: pillow ~=10.3
Requires-Dist: pillow-heif ~=0.16.0
Requires-Dist: geopy ~=2.4
Requires-Dist: rich ~=13.7
Requires-Dist: typer ~=0.12
Requires-Dist: fonttools ~=4.53
